ollamaocr_python/__init__.py
ollamaocr_python/ollamaocr.py
ollamaocr_python-0.1.1.dist-info/LICENSE
ollamaocr_python-0.1.1.dist-info/METADATA
ollamaocr_python-0.1.1.dist-info/WHEEL
ollamaocr_python-0.1.1.dist-info/top_level.txt
ollamaocr_python-0.1.1.dist-info/RECORD
