Metadata-Version: 2.1
Name: ollamaocr-python
Version: 0.1.1
Summary: ollamaocr with Llama vision
Home-page: https://github.com/Ga0512/ollamaocr-python
Author: Gabriel M. Cicotoste
Author-email: gabrielmurilocicotoste6@gmail.com
Classifier: Programming Language :: Python :: 3
Classifier: License :: OSI Approved :: MIT License
Classifier: Operating System :: OS Independent
Requires-Python: >=3.7
License-File: LICENSE
Requires-Dist: ollama
